fixedfig/__init__.py
fixedfig/core.py
fixedfig-0.1.6.dist-info/METADATA
fixedfig-0.1.6.dist-info/WHEEL
fixedfig-0.1.6.dist-info/top_level.txt
fixedfig-0.1.6.dist-info/RECORD
