Metadata-Version: 2.4
Name: fixedfig
Version: 0.1.6
Summary: A wrapper for matplotlib's plt.show() that globally sets figure window size, position, and target screen.
Requires-Python: >=3.8
Requires-Dist: matplotlib
Requires-Dist: pyglet==1.5.27
Dynamic: description
Dynamic: description-content-type
Dynamic: requires-dist
Dynamic: requires-python
Dynamic: summary
